{
    "total": [
        {
            "id": "540512512",
            "count": 293
        },
        {
            "id": "779743414",
            "count": 277
        },
        {
            "id": "1610800114",
            "count": 7
        },
        {
            "id": "100001631558405",
            "count": 0
        },
        {
            "id": "100002574000948",
            "count": 0
        },
        {
            "id": "100003341628080",
            "count": 0
        },
        {
            "id": "100005921221831",
            "count": 19
        },
        {
            "id": "100012199992153",
            "count": 44
        },
        {
            "id": "100015151637257",
            "count": 0
        },
        {
            "id": "100027983012630",
            "count": 125
        },
        {
            "id": "100029022785218",
            "count": 3
        },
        {
            "id": "100035731083424",
            "count": 127
        },
        {
            "id": "100036618382195",
            "count": 0
        },
        {
            "id": "100036947774673",
            "count": 24
        },
        {
            "id": "100037115165816",
            "count": 0
        },
        {
            "id": "100039903853101",
            "count": 15
        },
        {
            "id": "100040846521410",
            "count": 184
        },
        {
            "id": "100047975633711",
            "count": 8
        },
        {
            "id": "100056611602699",
            "count": 0
        },
        {
            "id": "100069279893724",
            "count": 1917
        },
        {
            "id": "100069527042075",
            "count": 0
        },
        {
            "id": "100070315661399",
            "count": 21
        },
        {
            "id": "100070863624856",
            "count": 126
        },
        {
            "id": "100072182030822",
            "count": 241
        },
        {
            "id": "100073280626414",
            "count": 25
        },
        {
            "id": "100073651845198",
            "count": 33
        },
        {
            "id": "100075401250019",
            "count": 19
        },
        {
            "id": "100077870917015",
            "count": 1
        },
        {
            "id": "100087675283094",
            "count": 2
        },
        {
            "id": "100091904264510",
            "count": 0
        },
        {
            "id": "100092405675956",
            "count": 0
        },
        {
            "id": "100094014555667",
            "count": 6
        },
        {
            "id": "100028939562771",
            "count": 8
        }
    ],
    "week": [
        {
            "id": "540512512",
            "count": 293
        },
        {
            "id": "779743414",
            "count": 277
        },
        {
            "id": "1610800114",
            "count": 7
        },
        {
            "id": "100001631558405",
            "count": 0
        },
        {
            "id": "100002574000948",
            "count": 0
        },
        {
            "id": "100003341628080",
            "count": 0
        },
        {
            "id": "100005921221831",
            "count": 19
        },
        {
            "id": "100012199992153",
            "count": 44
        },
        {
            "id": "100015151637257",
            "count": 0
        },
        {
            "id": "100027983012630",
            "count": 125
        },
        {
            "id": "100029022785218",
            "count": 3
        },
        {
            "id": "100035731083424",
            "count": 127
        },
        {
            "id": "100036618382195",
            "count": 0
        },
        {
            "id": "100036947774673",
            "count": 24
        },
        {
            "id": "100037115165816",
            "count": 0
        },
        {
            "id": "100039903853101",
            "count": 15
        },
        {
            "id": "100040846521410",
            "count": 184
        },
        {
            "id": "100047975633711",
            "count": 8
        },
        {
            "id": "100056611602699",
            "count": 0
        },
        {
            "id": "100069279893724",
            "count": 1917
        },
        {
            "id": "100069527042075",
            "count": 0
        },
        {
            "id": "100070315661399",
            "count": 21
        },
        {
            "id": "100070863624856",
            "count": 126
        },
        {
            "id": "100072182030822",
            "count": 241
        },
        {
            "id": "100073280626414",
            "count": 25
        },
        {
            "id": "100073651845198",
            "count": 33
        },
        {
            "id": "100075401250019",
            "count": 19
        },
        {
            "id": "100077870917015",
            "count": 1
        },
        {
            "id": "100087675283094",
            "count": 2
        },
        {
            "id": "100091904264510",
            "count": 0
        },
        {
            "id": "100092405675956",
            "count": 0
        },
        {
            "id": "100094014555667",
            "count": 6
        },
        {
            "id": "100028939562771",
            "count": 8
        }
    ],
    "day": [
        {
            "id": "540512512",
            "count": 293
        },
        {
            "id": "779743414",
            "count": 277
        },
        {
            "id": "1610800114",
            "count": 7
        },
        {
            "id": "100001631558405",
            "count": 0
        },
        {
            "id": "100002574000948",
            "count": 0
        },
        {
            "id": "100003341628080",
            "count": 0
        },
        {
            "id": "100005921221831",
            "count": 19
        },
        {
            "id": "100012199992153",
            "count": 44
        },
        {
            "id": "100015151637257",
            "count": 0
        },
        {
            "id": "100027983012630",
            "count": 125
        },
        {
            "id": "100029022785218",
            "count": 3
        },
        {
            "id": "100035731083424",
            "count": 127
        },
        {
            "id": "100036618382195",
            "count": 0
        },
        {
            "id": "100036947774673",
            "count": 24
        },
        {
            "id": "100037115165816",
            "count": 0
        },
        {
            "id": "100039903853101",
            "count": 15
        },
        {
            "id": "100040846521410",
            "count": 184
        },
        {
            "id": "100047975633711",
            "count": 8
        },
        {
            "id": "100056611602699",
            "count": 0
        },
        {
            "id": "100069279893724",
            "count": 1917
        },
        {
            "id": "100069527042075",
            "count": 0
        },
        {
            "id": "100070315661399",
            "count": 21
        },
        {
            "id": "100070863624856",
            "count": 126
        },
        {
            "id": "100072182030822",
            "count": 241
        },
        {
            "id": "100073280626414",
            "count": 25
        },
        {
            "id": "100073651845198",
            "count": 33
        },
        {
            "id": "100075401250019",
            "count": 19
        },
        {
            "id": "100077870917015",
            "count": 1
        },
        {
            "id": "100087675283094",
            "count": 2
        },
        {
            "id": "100091904264510",
            "count": 0
        },
        {
            "id": "100092405675956",
            "count": 0
        },
        {
            "id": "100094014555667",
            "count": 6
        },
        {
            "id": "100028939562771",
            "count": 8
        }
    ],
    "time": 5
}